arcgis_nb/__init__.py
arcgis_nb/arcgis.py
arcgis_nb-0.2.6.dist-info/METADATA
arcgis_nb-0.2.6.dist-info/WHEEL
arcgis_nb-0.2.6.dist-info/entry_points.txt
arcgis_nb-0.2.6.dist-info/top_level.txt
arcgis_nb-0.2.6.dist-info/RECORD
