Metadata-Version: 2.4
Name: arcgis_nb
Version: 0.2.6
Summary: A tool for extracting and processing LiDAR data for roofing projects in New Brunswick
Home-page: https://github.com/artisanroofing/arcgis_nb
Author: Amad Ud Din Gakkhar
Author-email: amad.gakkhar@adept-techsolutions.com
Classifier: Programming Language :: Python :: 3
Classifier: License :: OSI Approved :: MIT License
Classifier: Operating System :: OS Independent
Classifier: Development Status :: 4 - Beta
Classifier: Intended Audience :: Science/Research
Classifier: Topic :: Scientific/Engineering :: GIS
Requires-Python: >=3.7
Requires-Dist: requests
Requires-Dist: pyproj
Requires-Dist: pillow
Requires-Dist: matplotlib
Requires-Dist: numpy
Requires-Dist: opencv-python
Requires-Dist: laspy
Requires-Dist: geopandas
Requires-Dist: shapely
Requires-Dist: lazrs
Dynamic: author
Dynamic: author-email
Dynamic: classifier
Dynamic: description
Dynamic: description-content-type
Dynamic: home-page
Dynamic: requires-dist
Dynamic: requires-python
Dynamic: summary
